rxnrecer/__init__.py
rxnrecer/cli/__init__.py
rxnrecer/cli/cache.py
rxnrecer/cli/download.py
rxnrecer/cli/genmolsvg.py
rxnrecer/cli/predict.py
rxnrecer/config/__init__.py
rxnrecer/config/config.py
rxnrecer/lib/__init__.py
rxnrecer/lib/datasource/rhea.py
rxnrecer/lib/datasource/uniprot.py
rxnrecer/lib/embedding/esm_embedding.py
rxnrecer/lib/embedding/t5_embedding.py
rxnrecer/lib/embedding/unirep_embedding.py
rxnrecer/lib/evaluation/eva.py
rxnrecer/lib/llm/chat.py
rxnrecer/lib/llm/qa.py
rxnrecer/lib/ml/mlcommon.py
rxnrecer/lib/ml/mlpredict.py
rxnrecer/lib/model/mactive.py
rxnrecer/lib/rxn/Molecule.py
rxnrecer/lib/rxn/Reaction.py
rxnrecer/lib/rxn/process_all_reactions.py
rxnrecer/lib/smi/simi_caculator.py
rxnrecer/models/__init__.py
rxnrecer/models/bgru_model.py
rxnrecer/models/esm_embedding.py
rxnrecer/utils/__init__.py
rxnrecer/utils/bio_utils.py
rxnrecer/utils/ec_utils.py
rxnrecer/utils/evaluation_utils.py
rxnrecer/utils/file_utils.py
rxnrecer/utils/format_utils.py
rxnrecer/utils/rhea_utils.py
rxnrecer/utils/uniprot_utils.py
rxnrecer-1.3.7.dist-info/licenses/LICENSE
rxnrecer-1.3.7.dist-info/METADATA
rxnrecer-1.3.7.dist-info/WHEEL
rxnrecer-1.3.7.dist-info/entry_points.txt
rxnrecer-1.3.7.dist-info/top_level.txt
rxnrecer-1.3.7.dist-info/RECORD
