Metadata-Version: 2.4
Name: rxnrecer
Version: 1.3.7
Summary: Deep learning framework for predicting enzyme-catalyzed reactions from protein sequences
Author-email: RXNRECer Team <contact@rxnrecer.org>
Maintainer-email: Zhenkun Shi <zhenkun.shi@tib.cas.cn>
License-Expression: MIT
Project-URL: Homepage, https://github.com/kingstdio/RXNRECer
Project-URL: Documentation, https://github.com/kingstdio/RXNRECer#readme
Project-URL: Repository, https://github.com/kingstdio/RXNRECer.git
Project-URL: Issues, https://github.com/kingstdio/RXNRECer/issues
Project-URL: PyPI, https://pypi.org/project/rxnrecer/
Keywords: bioinformatics,enzyme,reaction,prediction,deep learning,protein
Classifier: Development Status :: 4 - Beta
Classifier: Intended Audience :: Science/Research
Classifier: Operating System :: OS Independent
Classifier: Programming Language :: Python :: 3
Classifier: Programming Language :: Python :: 3.10
Classifier: Programming Language :: Python :: 3.11
Classifier: Programming Language :: Python :: 3.12
Classifier: Topic :: Scientific/Engineering :: Bio-Informatics
Classifier: Topic :: Scientific/Engineering :: Artificial Intelligence
Requires-Python: >=3.10
License-File: LICENSE
Requires-Dist: torch>=2.0.0
Requires-Dist: numpy>=1.21.0
Requires-Dist: pandas>=1.3.0
Requires-Dist: scikit-learn>=1.0.0
Requires-Dist: biopython>=1.79
Requires-Dist: requests>=2.25.0
Requires-Dist: tqdm>=4.62.0
Requires-Dist: click>=8.0.0
Requires-Dist: openai>=1.0.0
Requires-Dist: anthropic>=0.7.0
Requires-Dist: boto3>=1.26.0
Requires-Dist: feather-format>=0.4.1
Requires-Dist: pyarrow>=10.0.0
Requires-Dist: fair-esm>=2.0.0
Requires-Dist: transformers>=4.20.0
Requires-Dist: pandarallel>=1.6.0
Requires-Dist: rdkit-pypi>=2022.9.3
Requires-Dist: sentencepiece>=0.1.99
Provides-Extra: dev
Requires-Dist: pytest>=6.0; extra == "dev"
Requires-Dist: pytest-cov>=2.0; extra == "dev"
Requires-Dist: black>=22.0; extra == "dev"
Requires-Dist: flake8>=4.0; extra == "dev"
Requires-Dist: mypy>=0.900; extra == "dev"
Provides-Extra: docs
Requires-Dist: sphinx>=4.0; extra == "docs"
Requires-Dist: sphinx-rtd-theme>=1.0; extra == "docs"
Requires-Dist: myst-parser>=0.15; extra == "docs"
Dynamic: license-file
